{"id": "1230508490218770436", "creation": 1582211060.0, "user_id": "229258137", "social_network": "twitter", "nsfw": false, "request": ["1aac5aa9-16ef-4aef-93e1-0b43ea7d03cb"], "metrics": {"1aac5aa9-16ef-4aef-93e1-0b43ea7d03cb": {"retweet_count": 0, "reply_count": 0, "like_count": 2, "quote_count": 0}}, "text": "I don\u2019t know who might need to read this atm. But I thought to share some food to feed your mind. \n\nAnd the message is from my best @nairamarleym1 song- \n\nDON\u2019T BREAK!\nDON\u2019T GIVEUP! \n\n#ThursdayMotivation #chloroquine https://t.co/DxOX9ScXpi", "first_save": 1635413522.816877, "hashtags": ["#THURSDAYMOTIVATION", "#CHLOROQUINE"]}