{"id": "1233473516357455873", "creation": 1582917977.0, "user_id": "620338365", "social_network": "twitter", "nsfw": false, "request": ["1aac5aa9-16ef-4aef-93e1-0b43ea7d03cb"], "metrics": {"1aac5aa9-16ef-4aef-93e1-0b43ea7d03cb": {"retweet_count": 0, "reply_count": 1, "like_count": 4, "quote_count": 0}}, "text": "Last week I\u2019ve been hearing #chloroquine cures COVID19\n\nI Thought your local champion went international #COVID19Nigeria\n\nNow that the Shege has landed can we handle it?", "first_save": 1635413522.816877, "geo": "0011746044ea662b", "hashtags": ["#CHLOROQUINE", "#COVID19NIGERIA"]}