{"id": "1240362046496989184", "creation": 1584560331.0, "user_id": "36937769", "social_network": "twitter", "nsfw": false, "request": ["1aac5aa9-16ef-4aef-93e1-0b43ea7d03cb"], "metrics": {"1aac5aa9-16ef-4aef-93e1-0b43ea7d03cb": {"retweet_count": 0, "reply_count": 0, "like_count": 0, "quote_count": 0}}, "text": "#chloroquine \n\nHere is the study and the paper that proves this is a cure for #WuhanVirus \n\nhttps://t.co/5KhunBKexX", "first_save": 1635413522.816877, "hashtags": ["#CHLOROQUINE", "#WUHANVIRUS"]}