{"id": "1240805879718408192", "creation": 1584666149.0, "user_id": "3013830860", "social_network": "twitter", "nsfw": false, "request": ["1aac5aa9-16ef-4aef-93e1-0b43ea7d03cb"], "metrics": {"1aac5aa9-16ef-4aef-93e1-0b43ea7d03cb": {"retweet_count": 22, "reply_count": 2, "like_count": 45, "quote_count": 2}}, "text": "#Chloroquine Already Used on #Coronavirus in US -- Study Shows 100% Success Rate -- And May Act as Preventative to Virus https://t.co/AD9hKdDBAV", "first_save": 1635413522.816877, "hashtags": ["#CHLOROQUINE", "#CORONAVIRUS"]}