{"id": "1240771850373869568", "creation": 1584658036.0, "user_id": "1067877551908012032", "social_network": "twitter", "nsfw": false, "request": ["1aac5aa9-16ef-4aef-93e1-0b43ea7d03cb"], "metrics": {"1aac5aa9-16ef-4aef-93e1-0b43ea7d03cb": {"retweet_count": 0, "reply_count": 0, "like_count": 0, "quote_count": 0}}, "quoted": "1240733667451789312", "text": "Used duck duck go, and here's the top hit for off label use:\n\"Off-label prescribing ... can be beneficial, especially when patients have exhausted all other approved options...\"\nhttps://t.co/HODu1hktay\n#Chloroquine https://t.co/PJ21hVDntn", "first_save": 1635413522.816877, "hashtags": ["#CHLOROQUINE"]}