{"id": "1240535481722470400", "creation": 1584601681.0, "user_id": "1170034640540897281", "social_network": "twitter", "nsfw": false, "request": ["1aac5aa9-16ef-4aef-93e1-0b43ea7d03cb"], "metrics": {"1aac5aa9-16ef-4aef-93e1-0b43ea7d03cb": {"retweet_count": 0, "reply_count": 0, "like_count": 0, "quote_count": 0}}, "text": "STRIVE TO SUCCEED TODAY, NO MATTER WHAT IT WILL COST YOU, BECAUSE THE REGRETS OF TOMORROW WILL EVEN COST YOU MORE PAIN\n\ud83d\udcab\ud83d\udcab\ud83d\udcab\ud83d\udcab\ud83d\udcab\ud83d\udcab\nMAKE MONEY FROM FIXED MATCH NOW YOU HAVE THE CHANCE, \ud83d\udcdeOR\ud83d\udce9 +2347014531233 \n\u23f3\u23f3\u23f3\u23f3\u23f3\u23f3\u23f3\nTHINK FIXED\u2705\nPLAY FIXED \u2705\nWIN \u2714\ufe0f\n#chloroquine #China", "first_save": 1635413522.816877, "hashtags": ["#CHLOROQUINE", "#CHINA"]}