{"id": "1241685897608904705", "creation": 1584875962.0, "user_id": "876462847357800449", "social_network": "twitter", "nsfw": false, "request": ["1aac5aa9-16ef-4aef-93e1-0b43ea7d03cb"], "metrics": {"1aac5aa9-16ef-4aef-93e1-0b43ea7d03cb": {"retweet_count": 0, "reply_count": 0, "like_count": 2, "quote_count": 0}}, "text": "China why? \n#COVID\u30fc19\n#COVIDIOT\n#CoronavirusPandemic \n#Nigeria \n#mothersday2020 \n#StayHome \n#Chloroquine \n#Quarantine \n#prayforitaly https://t.co/L98yZ1Adkp", "first_save": 1635413522.816877, "hashtags": ["#COVID\u30fc19", "#COVIDIOT", "#CORONAVIRUSPANDEMIC", "#NIGERIA", "#MOTHERSDAY2020", "#STAYHOME", "#CHLOROQUINE", "#QUARANTINE", "#PRAYFORITALY"]}