{"id": "1241450054457556993", "creation": 1584819732.0, "user_id": "46670837", "social_network": "twitter", "nsfw": false, "request": ["1aac5aa9-16ef-4aef-93e1-0b43ea7d03cb"], "metrics": {"1aac5aa9-16ef-4aef-93e1-0b43ea7d03cb": {"retweet_count": 1, "reply_count": 3, "like_count": 5, "quote_count": 1}}, "text": "#Chloroquine Hit &amp; trial.. nothing else. No such drug can work in viral diseases. Viruses are impregnable to quinine group, analogues and sulfa drugs or almost all antibiotics. \nTaking chloroquine or hydroxyquinone without supervision can be harmful in all likelihood.", "first_save": 1635413522.816877, "hashtags": ["#CHLOROQUINE"]}