{"id": "1242743446319828996", "creation": 1585128101.0, "user_id": "935937327989485571", "social_network": "twitter", "nsfw": false, "request": ["1aac5aa9-16ef-4aef-93e1-0b43ea7d03cb"], "metrics": {"1aac5aa9-16ef-4aef-93e1-0b43ea7d03cb": {"retweet_count": 0, "reply_count": 0, "like_count": 0, "quote_count": 0}}, "text": "All the information you need to know on the #chloroquine efficacy against #COVID-19 https://t.co/rF8D4B1sbP", "first_save": 1635413522.816877, "hashtags": ["#CHLOROQUINE", "#COVID"]}