{"id": "1242240715935100928", "creation": 1585008241.0, "user_id": "1050273192919601152", "social_network": "twitter", "nsfw": false, "request": ["1aac5aa9-16ef-4aef-93e1-0b43ea7d03cb"], "metrics": {"1aac5aa9-16ef-4aef-93e1-0b43ea7d03cb": {"retweet_count": 0, "reply_count": 0, "like_count": 0, "quote_count": 0}}, "text": "Please recognize that our lives are going to be disrupted for more than a few weeks. It'll be many months. And if they don't find temporary stopgaps, like #Chloroquine, then it'll be 6-18 months before life returns. Thanks. https://t.co/WTrIFz4UX3", "first_save": 1635413522.816877, "hashtags": ["#CHLOROQUINE"]}