{"id": "1242396719448502273", "creation": 1585045435.0, "user_id": "2147853925", "social_network": "twitter", "nsfw": false, "request": ["1aac5aa9-16ef-4aef-93e1-0b43ea7d03cb"], "metrics": {"1aac5aa9-16ef-4aef-93e1-0b43ea7d03cb": {"retweet_count": 2, "reply_count": 1, "like_count": 12, "quote_count": 0}}, "quoted": "1242194411783626765", "text": "#pharmacists in #Nigeria must speak with one voice against the indiscriminate use of #chloroquine.  @PSNYPG @AOAdebakin @kojere @UkamakaGladys @psnypg_lagos a  #COVID19 community of practice is required. #allhandsondeckNigeria #lesstalkmoreactionAfrica https://t.co/nsGiy3W2gb", "first_save": 1635413522.816877, "hashtags": ["#PHARMACISTS", "#NIGERIA", "#CHLOROQUINE", "#COVID19", "#ALLHANDSONDECKNIGERIA", "#LESSTALKMOREACTIONAFRICA"]}