{"id": "1242258898456723456", "creation": 1585012576.0, "user_id": "976512948540661762", "social_network": "twitter", "nsfw": false, "request": ["1aac5aa9-16ef-4aef-93e1-0b43ea7d03cb"], "metrics": {"1aac5aa9-16ef-4aef-93e1-0b43ea7d03cb": {"retweet_count": 0, "reply_count": 1, "like_count": 3, "quote_count": 0}}, "quoted": "1242212084647104514", "text": "When Trumpism kills.\n\nThe moment an Arizona woman realized the information bubble she lived in and the president she trusted was a liar, was the moment she and her husband lay dying.\n\nShe survived - her husband didn't. \n\n#MAGA2020 #COVID19 #Chloroquine https://t.co/ZkN8V6pO0p", "first_save": 1635413522.816877, "hashtags": ["#MAGA2020", "#COVID19", "#CHLOROQUINE"]}