{"id": "1242586689869991939", "creation": 1585090727.0, "user_id": "112296599", "social_network": "twitter", "nsfw": false, "request": ["1aac5aa9-16ef-4aef-93e1-0b43ea7d03cb"], "metrics": {"1aac5aa9-16ef-4aef-93e1-0b43ea7d03cb": {"retweet_count": 0, "reply_count": 1, "like_count": 0, "quote_count": 0}}, "text": "Man dies after confusing fishtank cleaner with a drug touted by #Drumpf #chloroquine #malaria #Covid19 https://t.co/e56BPToJRa", "first_save": 1635413522.816877, "hashtags": ["#DRUMPF", "#CHLOROQUINE", "#MALARIA", "#COVID19"]}