{"id": "1243616846949027840", "creation": 1585336336.0, "user_id": "21387044", "social_network": "twitter", "nsfw": false, "request": ["1aac5aa9-16ef-4aef-93e1-0b43ea7d03cb"], "metrics": {"1aac5aa9-16ef-4aef-93e1-0b43ea7d03cb": {"retweet_count": 0, "reply_count": 0, "like_count": 0, "quote_count": 0}}, "text": "My stepmom is in the same boat, trying to get her prescription filled. 3 places, 2 on back order, 1 that could fill 30days instead of 90days. All this because some people are promoting a miracle drug that hasn\u2019t even been properly tested yet. #chloroquine  https://t.co/VEHDIQ8dcL", "first_save": 1635413522.816877, "hashtags": ["#CHLOROQUINE"]}