{"id": "1246500579737767941", "creation": 1586023871.0, "user_id": "96766775", "social_network": "twitter", "nsfw": true, "request": ["1aac5aa9-16ef-4aef-93e1-0b43ea7d03cb"], "metrics": {"1aac5aa9-16ef-4aef-93e1-0b43ea7d03cb": {"retweet_count": 0, "reply_count": 1, "like_count": 0, "quote_count": 0}}, "text": "BREAKING! COVID-19 Drug Research: Study Shows That Hydroxychloroquine And Azithromycin Has No Effect On COVID-19 Patients, No Better Than A Dangerous Placebo - Thailand Medical News https://t.co/PJOhAKDkVr #Covid19NL  #chloroquine #fails", "first_save": 1635413522.816877, "hashtags": ["#COVID19NL", "#CHLOROQUINE", "#FAILS"]}