{"id": "1246874607380021257", "creation": 1586113046.0, "user_id": "897863213223751680", "social_network": "twitter", "nsfw": false, "request": ["1aac5aa9-16ef-4aef-93e1-0b43ea7d03cb"], "metrics": {"1aac5aa9-16ef-4aef-93e1-0b43ea7d03cb": {"retweet_count": 0, "reply_count": 0, "like_count": 0, "quote_count": 0}}, "quoted": "1246413112074547200", "text": "Action!\n\n#COVID2019 #COVID19france #france #Covid_19 #Petition #chloroquine #Hydroxychloroquine #Raoult #Raoult_didier #dousteblazy #Perronne https://t.co/VKhBpZcM5H", "first_save": 1635413522.816877, "hashtags": ["#COVID2019", "#COVID19FRANCE", "#FRANCE", "#COVID_19", "#PETITION", "#CHLOROQUINE", "#HYDROXYCHLOROQUINE", "#RAOULT", "#RAOULT_DIDIER", "#DOUSTEBLAZY", "#PERRONNE"]}