{"id": "1246968324745035782", "creation": 1586135390.0, "user_id": "978615531728195584", "social_network": "twitter", "nsfw": false, "request": ["1aac5aa9-16ef-4aef-93e1-0b43ea7d03cb"], "metrics": {"1aac5aa9-16ef-4aef-93e1-0b43ea7d03cb": {"retweet_count": 0, "reply_count": 0, "like_count": 0, "quote_count": 0}}, "quoted": "1246801663345618944", "text": "I was wondering about this! Do patients taking #chloroquine for other conditions get #COVID? This doc says yep they do. Bad news for these as virus inhibitors... Keep watching for more epidemiology on this though as this is only 1 report. #needmoredata https://t.co/vE2Zt1QCsd", "first_save": 1635413522.816877, "hashtags": ["#CHLOROQUINE", "#COVID", "#NEEDMOREDATA"]}