{"id": "1247994366368464896", "creation": 1586380018.0, "user_id": "1243384879305207809", "social_network": "twitter", "nsfw": false, "request": ["1aac5aa9-16ef-4aef-93e1-0b43ea7d03cb"], "metrics": {"1aac5aa9-16ef-4aef-93e1-0b43ea7d03cb": {"retweet_count": 0, "reply_count": 0, "like_count": 0, "quote_count": 0}}, "text": "Breaking news, comprehensive analysis shows #Hydroxychloroquine to be effective in over 98% of #coronavirus cases. \u201cResearchers can safely conclude over 98% of patients make a full recovery with #chloroquine administration, proving it effective.\u201d  #COVID\u30fc19 #COVID #COVIDIDIOT", "first_save": 1635413522.816877, "hashtags": ["#HYDROXYCHLOROQUINE", "#CORONAVIRUS", "#CHLOROQUINE", "#COVID\u30fc19", "#COVID", "#COVIDIDIOT"]}