{"id": "1252887888523481090", "creation": 1587546724.0, "user_id": "906921791695732736", "social_network": "twitter", "nsfw": true, "request": ["1aac5aa9-16ef-4aef-93e1-0b43ea7d03cb"], "metrics": {"1aac5aa9-16ef-4aef-93e1-0b43ea7d03cb": {"retweet_count": 0, "reply_count": 0, "like_count": 0, "quote_count": 0}}, "text": "Heart Face Mask https://t.co/G7ea0kItQj #facemasks #PPE #masks #ProtectNurses #HealthyAtHome #Hydroxychloroquine #NUFC #coronavirus #COVID\u30fc19 #Chloroquine #heart #Aldi #BigLittleLies #RHOBH #Cuomo #FF7R #selfie #Isolation #CoronavirusPandemic #Quarantine #IsolationBaking https://t.co/tET0ZwEjNt", "first_save": 1635413522.816877, "hashtags": ["#FACEMASKS", "#PPE", "#MASKS", "#PROTECTNURSES", "#HEALTHYATHOME", "#HYDROXYCHLOROQUINE", "#NUFC", "#CORONAVIRUS", "#COVID\u30fc19", "#CHLOROQUINE", "#HEART", "#ALDI", "#BIGLITTLELIES", "#RHOBH", "#CUOMO", "#FF7R", "#SELFIE", "#ISOLATION", "#CORONAVIRUSPANDEMIC", "#QUARANTINE", "#ISOLATIONBAKING"]}