{"id": "1253058246069243905", "creation": 1587587341.0, "user_id": "1159173006", "social_network": "twitter", "nsfw": false, "request": ["1aac5aa9-16ef-4aef-93e1-0b43ea7d03cb"], "metrics": {"1aac5aa9-16ef-4aef-93e1-0b43ea7d03cb": {"retweet_count": 1, "reply_count": 1, "like_count": 1, "quote_count": 0}}, "text": "#DrRickBright was fired from @NIH's BARDA for opposing the use of #chloroquine which turns out has no effect on #COVID19 except for fatal and debilitating side effects! #TrumpWillKillUsAll \nhttps://t.co/EtrooWisAt", "first_save": 1635413522.816877, "hashtags": ["#DRRICKBRIGHT", "#CHLOROQUINE", "#COVID19", "#TRUMPWILLKILLUSALL"]}