{"id": "1276811679112757248", "creation": 1593250600.0, "user_id": "37893536", "social_network": "twitter", "nsfw": false, "request": ["1aac5aa9-16ef-4aef-93e1-0b43ea7d03cb"], "metrics": {"1aac5aa9-16ef-4aef-93e1-0b43ea7d03cb": {"retweet_count": 32, "reply_count": 9, "like_count": 78, "quote_count": 7}}, "text": "Now 4 month taking #HCQ as #prevention, 100 mg every 3-4 days. (40 users) No side effect, apart of skin irritation in one user, who switched to #chloroquine.", "first_save": 1635413522.816877, "hashtags": ["#HCQ", "#PREVENTION", "#CHLOROQUINE"]}