{"id": "1026126827503452160", "creation": 1533482674.0, "user_id": "144737971", "social_network": "twitter", "nsfw": false, "request": ["73d2a602-56f5-43ee-a408-5fade8b46a2b"], "metrics": {"73d2a602-56f5-43ee-a408-5fade8b46a2b": {"retweet_count": 0, "reply_count": 0, "like_count": 0, "quote_count": 0}}, "text": "Periodic fasting starves cisplatin\u2010resistant cancers to death\n\nhttps://t.co/mxPMRnrAPx\n\n#cancer #science #research #fasting", "first_save": 1635869273.36451, "hashtags": ["#CANCER", "#SCIENCE", "#RESEARCH", "#FASTING"]}