{"id": "1133056535662346242", "creation": 1558976703.0, "user_id": "93837626", "social_network": "twitter", "nsfw": false, "request": ["a334fc7d-30d5-4f97-93ce-253b90c6701f"], "metrics": {"a334fc7d-30d5-4f97-93ce-253b90c6701f": {"retweet_count": 0, "reply_count": 0, "like_count": 0, "quote_count": 0}}, "text": "We campaign nationally to increase participation in #sport and #exercise because regular #physicalactivity can help with over 20 chronic diseases such as #TypeIIDiabetes, #CoronaryHeartDisease &amp; some forms of #Cancer.\n\nVisit\n\ud83d\udc49https://t.co/0UkzBPhFLP\n\ud83d\udc49https://t.co/2du7NUmRmJ https://t.co/waAcKDRoDj", "first_save": 1636370427.951254, "hashtags": ["#SPORT", "#EXERCISE", "#PHYSICALACTIVITY", "#TYPEIIDIABETES", "#CORONARYHEARTDISEASE", "#CANCER"]}