{"id": "1427871668454629381", "creation": 1629266108.0, "user_id": "386037376", "social_network": "twitter", "nsfw": false, "request": ["c6021839-e8e3-46c9-846b-13f958d14444"], "metrics": {"c6021839-e8e3-46c9-846b-13f958d14444": {"retweet_count": 3, "reply_count": 0, "like_count": 9, "quote_count": 0}}, "text": "Just voted NO in the #CArecall \n\nKeep @GavinNewsom \n\nReject the anti-science Trump sycophants who would ruin CA https://t.co/FKVDN6GnnQ", "first_save": 1655905508.830323, "hashtags": ["#CARECALL"]}