{"id": "1428212051999019010", "creation": 1629347262.0, "user_id": "67419276", "social_network": "twitter", "nsfw": false, "request": ["c6021839-e8e3-46c9-846b-13f958d14444"], "metrics": {"c6021839-e8e3-46c9-846b-13f958d14444": {"retweet_count": 0, "reply_count": 0, "like_count": 0, "quote_count": 0}}, "text": "Please vote no on the #CARecall! WE CAN'T HAVE THIS GUY BE OUR GOVERNOR: The most serious contender is Larry Elder, a conservative talk radio host who has called global warming \u201ca crock\u201d and says the minimum wage should be \u201czero-point-zero-zero.\u201d \ud83d\ude31", "first_save": 1655905508.830323, "hashtags": ["#CARECALL"]}