{"id": "1430227930152460288", "creation": 1629827885.0, "user_id": "18783905", "social_network": "twitter", "nsfw": false, "request": ["c6021839-e8e3-46c9-846b-13f958d14444"], "metrics": {"c6021839-e8e3-46c9-846b-13f958d14444": {"retweet_count": 0, "reply_count": 1, "like_count": 1, "quote_count": 1}}, "text": "How angry w/ @GavinNewsom are parents and teachers? Is the criticism fair ... or not? @1KatieOrr takes a look. #CARecall https://t.co/gZN2GWoNnM", "first_save": 1655905508.830323, "hashtags": ["#CARECALL"]}