{"id": "1432406429764227072", "creation": 1630347280.0, "user_id": "52591694", "social_network": "twitter", "nsfw": false, "request": ["c6021839-e8e3-46c9-846b-13f958d14444"], "metrics": {"c6021839-e8e3-46c9-846b-13f958d14444": {"retweet_count": 24, "reply_count": 1, "like_count": 23, "quote_count": 2}}, "text": "TODAY is the last day to register online to vote in the #CArecall \u2014 and get a ballot in the mail. Register to vote at https://t.co/7cyik0Hn7Q \n\nAfter today, you will have to register to vote at a polling place, vote center or your county elections office.\n\nhttps://t.co/AjNSYYg4Gc", "first_save": 1655905508.830323, "hashtags": ["#CARECALL"]}