{"id": "1432515984418553857", "creation": 1630373400.0, "user_id": "14885540", "social_network": "twitter", "nsfw": false, "request": ["c6021839-e8e3-46c9-846b-13f958d14444"], "metrics": {"c6021839-e8e3-46c9-846b-13f958d14444": {"retweet_count": 1, "reply_count": 0, "like_count": 4, "quote_count": 0}}, "text": "\"The Democratic Party doesn't really exist here in Imperial County,\" says Calexico council member Ra\u00fal Ure\u00f1a.\n\nIf these trends spread beyond the Imperial Valley, it could spell trouble for Gov. Gavin Newsom in the state's September 14 #CARecall.\nhttps://t.co/q6O7mZfIIl", "first_save": 1655905508.830323, "hashtags": ["#CARECALL"]}