{"id": "1435694931763359747", "creation": 1631131320.0, "user_id": "552983877", "social_network": "twitter", "nsfw": false, "request": ["c6021839-e8e3-46c9-846b-13f958d14444"], "metrics": {"c6021839-e8e3-46c9-846b-13f958d14444": {"retweet_count": 6, "reply_count": 0, "like_count": 15, "quote_count": 0}}, "text": "The GOP might win the #CARecall, but even if they (likely) lose they can make big $$ off the fake victimhood of a \"stolen\" election. So that makes it a win-win for them. https://t.co/vRhp8jbVOL", "first_save": 1655905508.830323, "hashtags": ["#CARECALL"]}