{"id": "1022140803844456450", "creation": 1532532332.0, "user_id": "254110693", "social_network": "twitter", "nsfw": false, "request": ["d47670bd-00d9-4b4b-b654-af12857ee504"], "metrics": {"d47670bd-00d9-4b4b-b654-af12857ee504": {"retweet_count": 20, "reply_count": 3, "like_count": 21, "quote_count": 1}}, "text": "We MUST take care of our #Veterans \u201cI talk to so many vets who claim they get benefits, but we need research,\u201d said @reptimwalz https://t.co/WwMgcVwNcE #Marijuana #Cannabis #MMJ @drphilroe @montel_williams @deptvetaffairs #pain #cancer #PTSD @davhq @vfwhq", "first_save": 1635509975.555947, "geo": "3b77caf94bfc81fe", "hashtags": ["#VETERANS", "#MARIJUANA", "#CANNABIS", "#MMJ", "#PAIN", "#CANCER", "#PTSD"]}