{"id": "1024064660276793344", "creation": 1532991015.0, "user_id": "902308339299663872", "social_network": "twitter", "nsfw": false, "request": ["d47670bd-00d9-4b4b-b654-af12857ee504"], "metrics": {"d47670bd-00d9-4b4b-b654-af12857ee504": {"retweet_count": 0, "reply_count": 0, "like_count": 1, "quote_count": 0}}, "quoted": "1024059599383609344", "text": "#MedicalUseCannabis helps pancreatic #cancer #patients live longer. #Cannabis #MedicalCannabis #CBD #cbdoils #cbdextract https://t.co/nxXTc95HRB", "first_save": 1635509975.555947, "hashtags": ["#MEDICALUSECANNABIS", "#CANCER", "#PATIENTS", "#CANNABIS", "#MEDICALCANNABIS", "#CBD", "#CBDOILS", "#CBDEXTRACT"]}