{"id": "1065276403724226561", "creation": 1542816661.0, "user_id": "345062377", "social_network": "twitter", "nsfw": false, "request": ["d47670bd-00d9-4b4b-b654-af12857ee504"], "metrics": {"d47670bd-00d9-4b4b-b654-af12857ee504": {"retweet_count": 0, "reply_count": 0, "like_count": 0, "quote_count": 0}}, "text": "Discover the truth about #cannabis and #cancer! Find out the facts in our latest blog post: https://t.co/B9SUVRLcQb\n#cancerresearch #CannabisLegalization #cannabiscanada #cancerawareness #KnowledgeIsPower https://t.co/bve0YozpKU", "first_save": 1635509975.555947, "hashtags": ["#CANNABIS", "#CANCER", "#CANCERRESEARCH", "#CANNABISLEGALIZATION", "#CANNABISCANADA", "#CANCERAWARENESS", "#KNOWLEDGEISPOWER"]}