{"id": "1086940054465990656", "creation": 1547981678.0, "user_id": "277042197", "social_network": "twitter", "nsfw": false, "request": ["d47670bd-00d9-4b4b-b654-af12857ee504"], "metrics": {"d47670bd-00d9-4b4b-b654-af12857ee504": {"retweet_count": 1, "reply_count": 0, "like_count": 2, "quote_count": 0}}, "text": "Major #cannabis #cancer study planned in Canada to prove whether cannabis helps cancer symptoms such as pain, sleep loss, anxiety and nausea #EndOurPain https://t.co/4fAOufT1Um https://t.co/XqOMls8Az2", "first_save": 1635509975.555947, "hashtags": ["#CANNABIS", "#CANCER", "#ENDOURPAIN"]}