{"id": "1092380948069523457", "creation": 1549278888.0, "user_id": "1543206234", "social_network": "twitter", "nsfw": false, "request": ["d47670bd-00d9-4b4b-b654-af12857ee504"], "metrics": {"d47670bd-00d9-4b4b-b654-af12857ee504": {"retweet_count": 3, "reply_count": 0, "like_count": 3, "quote_count": 3}}, "text": "\"The TRUTH about CHEMO\"\n\nSuccess ratio of chemotherapy (2%):\nhttps://t.co/hQB0cj5esu\n\nOncologists make huge profits, as much as two-thirds of their income in some cases, from chemotherapy drugs. \n\n#WorldCancerDay\n#Cancer #Chemotherapy #Oncology \n#BigPharma #Legalize #Cannabis https://t.co/74HUFapEUF", "first_save": 1635509975.555947, "hashtags": ["#WORLDCANCERDAY", "#CANCER", "#CHEMOTHERAPY", "#ONCOLOGY", "#BIGPHARMA", "#LEGALIZE", "#CANNABIS"]}