{"id": "1105078341017702400", "creation": 1552306182.0, "user_id": "1054756281930649600", "social_network": "twitter", "nsfw": false, "request": ["d47670bd-00d9-4b4b-b654-af12857ee504"], "metrics": {"d47670bd-00d9-4b4b-b654-af12857ee504": {"retweet_count": 0, "reply_count": 0, "like_count": 0, "quote_count": 0}}, "text": "ReeferReporters: \u201c #Police search #Missouri #cancer #patient patient\u2019s bags for #marijuana in video\u201d\n\n#usa #medicalmarijuana #cannabis #patient #illegalsearch  https://t.co/b26QDaIG2Z", "first_save": 1635509975.555947, "hashtags": ["#POLICE", "#MISSOURI", "#CANCER", "#PATIENT", "#MARIJUANA", "#USA", "#MEDICALMARIJUANA", "#CANNABIS", "#PATIENT", "#ILLEGALSEARCH"]}