{"id": "1140588029733691392", "creation": 1560772352.0, "user_id": "1054756281930649600", "social_network": "twitter", "nsfw": false, "request": ["d47670bd-00d9-4b4b-b654-af12857ee504"], "metrics": {"d47670bd-00d9-4b4b-b654-af12857ee504": {"retweet_count": 0, "reply_count": 0, "like_count": 0, "quote_count": 0}}, "text": "BowmanTimmothy: RT @WeedStocksNews: Exposed: The #cannabis oil sales reps breaking the law with unproven claims about it 'treating #cancer'\n\nhttps://t.co/3KOzwABhKx", "first_save": 1635509975.555947, "hashtags": ["#CANNABIS", "#CANCER"]}