{"id": "1145039596981510144", "creation": 1561833688.0, "user_id": "2316255284", "social_network": "twitter", "nsfw": false, "request": ["d47670bd-00d9-4b4b-b654-af12857ee504"], "metrics": {"d47670bd-00d9-4b4b-b654-af12857ee504": {"retweet_count": 0, "reply_count": 0, "like_count": 0, "quote_count": 0}}, "text": "Forgot to post this pic of me and my love \u2764\u2764 \nPS. 6 days till my bday!!!\n.\n.\n.\n#420couple #420family #420life #cannabiscommunity #cannabis #polyamorous #bi #lgbtq #i502 #bdaysoon #julybaby #cancer #cancerbaby\u2026 https://t.co/pokrScTY28", "first_save": 1635509975.555947, "hashtags": ["#420COUPLE", "#420FAMILY", "#420LIFE", "#CANNABISCOMMUNITY", "#CANNABIS", "#POLYAMOROUS", "#BI", "#LGBTQ", "#I502", "#BDAYSOON", "#JULYBABY", "#CANCER", "#CANCERBABY"]}