{"id": "1153924366779977728", "creation": 1563951982.0, "user_id": "937616506447433728", "social_network": "twitter", "nsfw": false, "request": ["d47670bd-00d9-4b4b-b654-af12857ee504"], "metrics": {"d47670bd-00d9-4b4b-b654-af12857ee504": {"retweet_count": 0, "reply_count": 1, "like_count": 1, "quote_count": 0}}, "text": "April 2019 - Medical Cannabis and Colorectal Cancer Webinar by @FightCRC #cancer #cannabis https://t.co/YcdaMfAo1r via @SlideShare", "first_save": 1635509975.555947, "hashtags": ["#CANCER", "#CANNABIS"]}