{"id": "1168003295903793156", "creation": 1567308660.0, "user_id": "807699330165600256", "social_network": "twitter", "nsfw": false, "request": ["d47670bd-00d9-4b4b-b654-af12857ee504"], "metrics": {"d47670bd-00d9-4b4b-b654-af12857ee504": {"retweet_count": 0, "reply_count": 0, "like_count": 1, "quote_count": 0}}, "text": "Could FBL-03G, a #cannabis #flavonoid derivative, be a key for treating pancreatic cancer?\n\nhttps://t.co/sZPfGvP2ag\n#marijuana #research #cancer #pancreaticcancer #fbl03g #cannabinoid #science #healthcare @AmericanCancer", "first_save": 1635509975.555947, "hashtags": ["#CANNABIS", "#FLAVONOID", "#MARIJUANA", "#RESEARCH", "#CANCER", "#PANCREATICCANCER", "#FBL03G", "#CANNABINOID", "#SCIENCE", "#HEALTHCARE"]}