{"id": "1216699327059349505", "creation": 1578918699.0, "user_id": "2478910584", "social_network": "twitter", "nsfw": false, "request": ["d47670bd-00d9-4b4b-b654-af12857ee504"], "metrics": {"d47670bd-00d9-4b4b-b654-af12857ee504": {"retweet_count": 0, "reply_count": 0, "like_count": 0, "quote_count": 0}}, "text": "What Is CBG (and Is It the New CBD)?\n#CBD #Cannabidiol #Hemp #Cannabis #CBDHemp #HempCBD #LungCancer #Cancer #MedicalCannibis #CBG\n#CBDMedicine #HempMeds #RSHO #CBDoil  #MyHealthIsBetter #ShopCBD #HempOils #CBDNews #CBDresearch @ShopCBDHempOils\nhttps://t.co/TRu7Xe0N5i", "first_save": 1635509975.555947, "hashtags": ["#CBD", "#CANNABIDIOL", "#HEMP", "#CANNABIS", "#CBDHEMP", "#HEMPCBD", "#LUNGCANCER", "#CANCER", "#MEDICALCANNIBIS", "#CBG", "#CBDMEDICINE", "#HEMPMEDS", "#RSHO", "#CBDOIL", "#MYHEALTHISBETTER", "#SHOPCBD", "#HEMPOILS", "#CBDNEWS", "#CBDRESEARCH"]}