{"id": "1219726064064311303", "creation": 1579640329.0, "user_id": "543761210", "social_network": "twitter", "nsfw": false, "request": ["d47670bd-00d9-4b4b-b654-af12857ee504"], "metrics": {"d47670bd-00d9-4b4b-b654-af12857ee504": {"retweet_count": 1, "reply_count": 0, "like_count": 2, "quote_count": 0}}, "quoted": "1219679236425965568", "text": "#BernieSanders is taking on #StatusQuo of #Republicans and #Democrats of the #RulingClass of #AmericaFirst she is trying to protect her money from being #Taxed ~ #Cannabis is a vegetable was always food if we eat it we prevent #Cancer ~ #Science #GodLevel \nhttps://t.co/iJ4mOR3JWa https://t.co/GOeKNSzNfT", "first_save": 1635509975.555947, "hashtags": ["#BERNIESANDERS", "#STATUSQUO", "#REPUBLICANS", "#DEMOCRATS", "#RULINGCLASS", "#AMERICAFIRST", "#TAXED", "#CANNABIS", "#CANCER", "#SCIENCE", "#GODLEVEL"]}