{"id": "1226606234238955520", "creation": 1581280690.0, "user_id": "543761210", "social_network": "twitter", "nsfw": false, "request": ["d47670bd-00d9-4b4b-b654-af12857ee504"], "metrics": {"d47670bd-00d9-4b4b-b654-af12857ee504": {"retweet_count": 0, "reply_count": 0, "like_count": 0, "quote_count": 0}}, "quoted": "1226535283547660288", "text": "#CBS does not want #Americans to have #MedicareForAll #Cannabis access to food that prevents #Cancer that #God gave us ~ #Gaslighting #AmericanVoters for #FOSSILS #WARS #Pharmaceutical #God needs a #Movement can we use @OurRevolution @justicedems @BrandNew535 please? #Bernie2020 https://t.co/o3yBrjSOGj https://t.co/UJFcbVCIwj", "first_save": 1635509975.555947, "hashtags": ["#CBS", "#AMERICANS", "#MEDICAREFORALL", "#CANNABIS", "#CANCER", "#GOD", "#GASLIGHTING", "#AMERICANVOTERS", "#FOSSILS", "#WARS", "#PHARMACEUTICAL", "#GOD", "#MOVEMENT", "#BERNIE2020"]}