{"id": "1279512992812535809", "creation": 1593894644.0, "user_id": "543761210", "social_network": "twitter", "nsfw": false, "request": ["d47670bd-00d9-4b4b-b654-af12857ee504"], "metrics": {"d47670bd-00d9-4b4b-b654-af12857ee504": {"retweet_count": 0, "reply_count": 0, "like_count": 2, "quote_count": 0}}, "text": "If #Cannabis can #Treat #Cancer #Imagine if we at the green leafy veggie to #Prevent #Disease and provide #ImmuneSupport ~ https://t.co/1nbSTk4edU", "first_save": 1635509975.555947, "hashtags": ["#CANNABIS", "#TREAT", "#CANCER", "#IMAGINE", "#PREVENT", "#DISEASE", "#IMMUNESUPPORT"]}