{"id": "128944815890112512", "creation": 1319577814.0, "user_id": "230883057", "social_network": "twitter", "nsfw": false, "request": ["d47670bd-00d9-4b4b-b654-af12857ee504"], "metrics": {"d47670bd-00d9-4b4b-b654-af12857ee504": {"retweet_count": 0, "reply_count": 0, "like_count": 0, "quote_count": 0}}, "text": "Juicing Raw Cannabis For Greater Health http://t.co/ddSoYQ1Y via @herbalhealthsys #Cannabis #Marijuana #MMJ #Health #Cancer", "first_save": 1635509975.555947, "hashtags": ["#CANNABIS", "#MARIJUANA", "#MMJ", "#HEALTH", "#CANCER"]}