{"id": "1330948619898290176", "creation": 1606157853.0, "user_id": "1158481123938201600", "social_network": "twitter", "nsfw": false, "request": ["d47670bd-00d9-4b4b-b654-af12857ee504"], "metrics": {"d47670bd-00d9-4b4b-b654-af12857ee504": {"retweet_count": 6, "reply_count": 0, "like_count": 6, "quote_count": 0}}, "text": "The following review explores #CBD as a treatment for #cancer. Researchers highlight the associated anti-proliferative, pro-apoptotic, cytotoxic, anti-invasive, anti-angiogenic, anti-inflammatory &amp; immunomodulatory effects. #Cannabis #Mmemberville https://t.co/OzqTA2kJzg", "first_save": 1635509975.555947, "hashtags": ["#CBD", "#CANCER", "#CANNABIS", "#MMEMBERVILLE"]}