{"id": "173435384364142593", "creation": 1330185192.0, "user_id": "86215122", "social_network": "twitter", "nsfw": false, "request": ["d47670bd-00d9-4b4b-b654-af12857ee504"], "metrics": {"d47670bd-00d9-4b4b-b654-af12857ee504": {"retweet_count": 0, "reply_count": 0, "like_count": 0, "quote_count": 0}}, "text": "http://t.co/QlVhsPCe Missoula Toddler Now Cancer-Free #cannabis #hemp #marijuana #health #medecine #cancer #law #justice #policy #peace", "first_save": 1635509975.555947, "hashtags": ["#CANNABIS", "#HEMP", "#MARIJUANA", "#HEALTH", "#MEDECINE", "#CANCER", "#LAW", "#JUSTICE", "#POLICY", "#PEACE"]}