{"id": "357339149256241153", "creation": 1374031266.0, "user_id": "1278464438", "social_network": "twitter", "nsfw": false, "request": ["d47670bd-00d9-4b4b-b654-af12857ee504"], "metrics": {"d47670bd-00d9-4b4b-b654-af12857ee504": {"retweet_count": 0, "reply_count": 1, "like_count": 1, "quote_count": 0}}, "text": "How Weed Works...Scientifically http://t.co/Sml90yA40k via @HuffPostLive @bravemykayla #Cannabis #marijuana #mmj #hope #cure #cancer #dravet", "first_save": 1635509975.555947, "hashtags": ["#CANNABIS", "#MARIJUANA", "#MMJ", "#HOPE", "#CURE", "#CANCER", "#DRAVET"]}