{"id": "360502415109275648", "creation": 1374785448.0, "user_id": "403732127", "social_network": "twitter", "nsfw": false, "request": ["d47670bd-00d9-4b4b-b654-af12857ee504"], "metrics": {"d47670bd-00d9-4b4b-b654-af12857ee504": {"retweet_count": 0, "reply_count": 0, "like_count": 0, "quote_count": 0}}, "text": "Always worth a re-share : #PastCannabisNews:\n#Spain #Study Confirms #Cannabis #Oil #Cures #Cancer Without Side... http://t.co/E4wiVj8nJL", "first_save": 1635509975.555947, "hashtags": ["#PASTCANNABISNEWS", "#SPAIN", "#STUDY", "#CANNABIS", "#OIL", "#CURES", "#CANCER"]}