{"id": "406825879780618240", "creation": 1385829822.0, "user_id": "732951152", "social_network": "twitter", "nsfw": false, "request": ["d47670bd-00d9-4b4b-b654-af12857ee504"], "metrics": {"d47670bd-00d9-4b4b-b654-af12857ee504": {"retweet_count": 0, "reply_count": 0, "like_count": 0, "quote_count": 0}}, "text": "Join us live in 20 mins in wishing #RickSimpson a Happy Birthday! http://t.co/cTQGchzIYM #Cannabis=#cancer #cure #RickSimpsonOil #RSO #hemp", "first_save": 1635509975.555947, "hashtags": ["#RICKSIMPSON", "#CANNABIS", "#CANCER", "#CURE", "#RICKSIMPSONOIL", "#RSO", "#HEMP"]}