{"id": "492302966791999488", "creation": 1406209148.0, "user_id": "29954112", "social_network": "twitter", "nsfw": false, "request": ["d47670bd-00d9-4b4b-b654-af12857ee504"], "metrics": {"d47670bd-00d9-4b4b-b654-af12857ee504": {"retweet_count": 0, "reply_count": 0, "like_count": 0, "quote_count": 0}}, "text": "#Scientists reveal how THC \u2013 found in #cannabis \u2013 \u2018could slow #cancer tumour growth\u2019 | http://t.co/EFmBIUKWVk http://t.co/AvMydjb148", "first_save": 1635509975.555947, "hashtags": ["#SCIENTISTS", "#CANNABIS", "#CANCER"]}