{"id": "493421534195630080", "creation": 1406475835.0, "user_id": "17723367", "social_network": "twitter", "nsfw": false, "request": ["d47670bd-00d9-4b4b-b654-af12857ee504"], "metrics": {"d47670bd-00d9-4b4b-b654-af12857ee504": {"retweet_count": 39, "reply_count": 0, "like_count": 20, "quote_count": 0}}, "text": "We do not need to find the cure for cancer. We need to legalize the cure for cancer !  #cancer #cure #cannabis #mmj http://t.co/ObVatnp5Xs", "first_save": 1635509975.555947, "hashtags": ["#CANCER", "#CURE", "#CANNABIS", "#MMJ"]}