{"id": "575803935472115712", "creation": 1426117330.0, "user_id": "1295966095", "social_network": "twitter", "nsfw": false, "request": ["d47670bd-00d9-4b4b-b654-af12857ee504"], "metrics": {"d47670bd-00d9-4b4b-b654-af12857ee504": {"retweet_count": 6, "reply_count": 0, "like_count": 10, "quote_count": 0}}, "text": "#Cannabis treats a variety of illnesses,  MS, #cancer, #epilepsy &amp; #seizures. Wrong for #patients &amp; doctors to fear prosecution. #california", "first_save": 1635509975.555947, "geo": "6c686af766d8429c", "hashtags": ["#CANNABIS", "#CANCER", "#EPILEPSY", "#SEIZURES", "#PATIENTS", "#CALIFORNIA"]}