{"id": "589971752517763072", "creation": 1429495201.0, "user_id": "68754498", "social_network": "twitter", "nsfw": false, "request": ["d47670bd-00d9-4b4b-b654-af12857ee504"], "metrics": {"d47670bd-00d9-4b4b-b654-af12857ee504": {"retweet_count": 19, "reply_count": 1, "like_count": 6, "quote_count": 0}}, "text": "The US Finally Admits #Cannabis Kills #Cancer Cells http://t.co/PkdU8Kw3O1 @NORML @FDA_Drug_Info @US_FDA @CDCgov http://t.co/lO8EQhO0w6", "first_save": 1635509975.555947, "hashtags": ["#CANNABIS", "#CANCER"]}