{"id": "636669892247158784", "creation": 1440628905.0, "user_id": "2522443332", "social_network": "twitter", "nsfw": false, "request": ["d47670bd-00d9-4b4b-b654-af12857ee504"], "metrics": {"d47670bd-00d9-4b4b-b654-af12857ee504": {"retweet_count": 1, "reply_count": 0, "like_count": 3, "quote_count": 0}}, "text": "11-year study shows #cannabis users have lower risk of #bladder #cancer. #marijuana - http://t.co/xRm9E4jv7i", "first_save": 1635509975.555947, "hashtags": ["#CANNABIS", "#BLADDER", "#CANCER", "#MARIJUANA"]}