{"id": "648360069172699136", "creation": 1443416061.0, "user_id": "2591719886", "social_network": "twitter", "nsfw": false, "request": ["d47670bd-00d9-4b4b-b654-af12857ee504"], "metrics": {"d47670bd-00d9-4b4b-b654-af12857ee504": {"retweet_count": 0, "reply_count": 0, "like_count": 0, "quote_count": 0}}, "text": "#Cannabidiol as potential anticancer drug\nhttp://t.co/XLt1RNUMbN\n\n#MME #cancer #medicalmarijuana #cannabis #cbd http://t.co/ZzqAhOgsrp", "first_save": 1635509975.555947, "hashtags": ["#CANNABIDIOL", "#MME", "#CANCER", "#MEDICALMARIJUANA", "#CANNABIS", "#CBD"]}