{"id": "653034179047747584", "creation": 1444530455.0, "user_id": "198173233", "social_network": "twitter", "nsfw": false, "request": ["d47670bd-00d9-4b4b-b654-af12857ee504"], "metrics": {"d47670bd-00d9-4b4b-b654-af12857ee504": {"retweet_count": 0, "reply_count": 0, "like_count": 0, "quote_count": 0}}, "text": "9 TYPES O #CANCER THAT CAN BE KILLED BY #CANNABIS HERE\u2019S HOW brain breast lung prost8 blood liver pancreas @mikebonin http://t.co/MX3sXpYo7e", "first_save": 1635509975.555947, "hashtags": ["#CANCER", "#CANNABIS"]}