{"id": "654259183399866368", "creation": 1444822519.0, "user_id": "2588614772", "social_network": "twitter", "nsfw": false, "request": ["d47670bd-00d9-4b4b-b654-af12857ee504"], "metrics": {"d47670bd-00d9-4b4b-b654-af12857ee504": {"retweet_count": 0, "reply_count": 0, "like_count": 0, "quote_count": 0}}, "text": "#Cancer patient given 18 months to live is 'cured by #Cannabis'\n\nhttp://t.co/j7eEXwSdsM \u2026  #marijuana #cannabis #cbd http://t.co/pXxk4QHvm2", "first_save": 1635509975.555947, "hashtags": ["#CANCER", "#CANNABIS", "#MARIJUANA", "#CANNABIS", "#CBD"]}