{"id": "673947567353233410", "creation": 1449516596.0, "user_id": "437673995", "social_network": "twitter", "nsfw": false, "request": ["d47670bd-00d9-4b4b-b654-af12857ee504"], "metrics": {"d47670bd-00d9-4b4b-b654-af12857ee504": {"retweet_count": 1, "reply_count": 0, "like_count": 0, "quote_count": 0}}, "quoted": "672164695814635520", "text": "Talk about #cancer? We run for it. \nTalk about #fukushima, #opchemtrails, #cdcfraud, #cannabis...\n@cancersociety  https://t.co/KtE3ut1B1b", "first_save": 1635509975.555947, "hashtags": ["#CANCER", "#FUKUSHIMA", "#OPCHEMTRAILS", "#CDCFRAUD", "#CANNABIS"]}