{"id": "687232445142425600", "creation": 1452683957.0, "user_id": "27615701", "social_network": "twitter", "nsfw": false, "request": ["d47670bd-00d9-4b4b-b654-af12857ee504"], "metrics": {"d47670bd-00d9-4b4b-b654-af12857ee504": {"retweet_count": 3, "reply_count": 0, "like_count": 1, "quote_count": 0}}, "text": "David #Bowie's #son reveals he backs #medical #marijuana #cannabis - as his #cancer -stricken wife finds 'a ... https://t.co/cqyWVyrzC1", "first_save": 1635509975.555947, "hashtags": ["#BOWIE", "#SON", "#MEDICAL", "#MARIJUANA", "#CANNABIS", "#CANCER"]}