{"id": "758697477759467520", "creation": 1469722549.0, "user_id": "132176311", "social_network": "twitter", "nsfw": false, "request": ["d47670bd-00d9-4b4b-b654-af12857ee504"], "metrics": {"d47670bd-00d9-4b4b-b654-af12857ee504": {"retweet_count": 0, "reply_count": 0, "like_count": 0, "quote_count": 0}}, "text": "The latest The Boom Boom Daily! https://t.co/6KUhm2AKwq Thanks to @ArtistSoSexi @BrianJMoylan @ConnerHabib #cancer #cannabis", "first_save": 1635509975.555947, "hashtags": ["#CANCER", "#CANNABIS"]}