{"id": "798799773595680768", "creation": 1479283681.0, "user_id": "119074969", "social_network": "twitter", "nsfw": false, "request": ["d47670bd-00d9-4b4b-b654-af12857ee504"], "metrics": {"d47670bd-00d9-4b4b-b654-af12857ee504": {"retweet_count": 2, "reply_count": 0, "like_count": 3, "quote_count": 0}}, "text": "The Homemade #CannabisOil Recipe\n\n#People Are Using To Treat #Cancer https://t.co/n2ibM3DAFM #MedicalCannabis #Cannabis https://t.co/1Fhfm8Yrfu", "first_save": 1635509975.555947, "hashtags": ["#CANNABISOIL", "#PEOPLE", "#CANCER", "#MEDICALCANNABIS", "#CANNABIS"]}