{"id": "809477126126596096", "creation": 1481829360.0, "user_id": "750776392749453312", "social_network": "twitter", "nsfw": false, "request": ["d47670bd-00d9-4b4b-b654-af12857ee504"], "metrics": {"d47670bd-00d9-4b4b-b654-af12857ee504": {"retweet_count": 0, "reply_count": 0, "like_count": 0, "quote_count": 0}}, "text": "#Cannabis in the Fight Against #BreastCancer https://t.co/NwjMWZ6Z3a #healing #herbal #ganja #marijuana #cancer", "first_save": 1635509975.555947, "hashtags": ["#CANNABIS", "#BREASTCANCER", "#HEALING", "#HERBAL", "#GANJA", "#MARIJUANA", "#CANCER"]}