{"id": "830516509147557888", "creation": 1486845540.0, "user_id": "766305667762229248", "social_network": "twitter", "nsfw": false, "request": ["d47670bd-00d9-4b4b-b654-af12857ee504"], "metrics": {"d47670bd-00d9-4b4b-b654-af12857ee504": {"retweet_count": 0, "reply_count": 0, "like_count": 0, "quote_count": 0}}, "text": "The Next Big Brain #Cancer Drug Could Come from #Marijuana https://t.co/Og3szUkVo3 #cannabis #mmj", "first_save": 1635509975.555947, "hashtags": ["#CANCER", "#MARIJUANA", "#CANNABIS", "#MMJ"]}