{"id": "832925006334193665", "creation": 1487419771.0, "user_id": "345133626", "social_network": "twitter", "nsfw": false, "request": ["d47670bd-00d9-4b4b-b654-af12857ee504"], "metrics": {"d47670bd-00d9-4b4b-b654-af12857ee504": {"retweet_count": 1, "reply_count": 0, "like_count": 2, "quote_count": 0}}, "text": "The Power Of #Cannabis Sheds Light In The Fight Against Brain Cancer https://t.co/P7pyahrPGZ #svpol #marijuana #weed #nomoredrugwar #cancer", "first_save": 1635509975.555947, "hashtags": ["#CANNABIS", "#SVPOL", "#MARIJUANA", "#WEED", "#NOMOREDRUGWAR", "#CANCER"]}