{"id": "880881160859111426", "creation": 1498853409.0, "user_id": "245212452", "social_network": "twitter", "nsfw": false, "request": ["d47670bd-00d9-4b4b-b654-af12857ee504"], "metrics": {"d47670bd-00d9-4b4b-b654-af12857ee504": {"retweet_count": 0, "reply_count": 0, "like_count": 0, "quote_count": 0}}, "text": "#Cancer &amp; #Cannabis stories that give great insight about the many wonders of this plant. https://t.co/ar5AYAFhPQ https://t.co/pwk0KWnq8O", "first_save": 1635509975.555947, "hashtags": ["#CANCER", "#CANNABIS"]}