{"id": "931973478764331008", "creation": 1511034767.0, "user_id": "856902981211619328", "social_network": "twitter", "nsfw": false, "request": ["d47670bd-00d9-4b4b-b654-af12857ee504"], "metrics": {"d47670bd-00d9-4b4b-b654-af12857ee504": {"retweet_count": 0, "reply_count": 0, "like_count": 0, "quote_count": 0}}, "text": "Cannabis advocacy group to hold petition signing event in Southern Utah https://t.co/j4I6yfwFhs #thc #cbd #utah #advocacy #cancer #cannabis @utahpatients https://t.co/Meudk5zepn", "first_save": 1635509975.555947, "hashtags": ["#THC", "#CBD", "#UTAH", "#ADVOCACY", "#CANCER", "#CANNABIS"]}