{"id": "933872470871937034", "creation": 1511487522.0, "user_id": "810621013666988032", "social_network": "twitter", "nsfw": false, "request": ["d47670bd-00d9-4b4b-b654-af12857ee504"], "metrics": {"d47670bd-00d9-4b4b-b654-af12857ee504": {"retweet_count": 6, "reply_count": 0, "like_count": 3, "quote_count": 0}}, "text": "This story is not an isolated one. Why are hundreds of thousands of sick Australians being refused access to #Cannabis as medicine?\nAustralians are able to grow their own cannabis, so the easiest &amp; fastest way to stop the suffering is a #CannabisAmnesty.\n#AUSPOL #Cancer #Epilepsy https://t.co/5ZujnJGDgI", "first_save": 1635509975.555947, "hashtags": ["#CANNABIS", "#CANNABISAMNESTY", "#AUSPOL", "#CANCER", "#EPILEPSY"]}