{"id": "949015512125788160", "creation": 1515097904.0, "user_id": "520983527", "social_network": "twitter", "nsfw": false, "request": ["d47670bd-00d9-4b4b-b654-af12857ee504"], "metrics": {"d47670bd-00d9-4b4b-b654-af12857ee504": {"retweet_count": 0, "reply_count": 0, "like_count": 0, "quote_count": 0}}, "text": "Some History Behind CBD ##CBD ##CBDHealthy #cancer #cannabis #history #marijuana #medicine #seizures https://t.co/o3Kl0fTcVG https://t.co/9TRkGODpMt", "first_save": 1635509975.555947, "hashtags": ["#CBD", "#CBDHEALTHY", "#CANCER", "#CANNABIS", "#HISTORY", "#MARIJUANA", "#MEDICINE", "#SEIZURES"]}