{"id": "975062589720924160", "creation": 1521308011.0, "user_id": "3980409262", "social_network": "twitter", "nsfw": false, "request": ["d47670bd-00d9-4b4b-b654-af12857ee504"], "metrics": {"d47670bd-00d9-4b4b-b654-af12857ee504": {"retweet_count": 0, "reply_count": 0, "like_count": 0, "quote_count": 0}}, "text": "If you state \u201c should cannabis be sold in vegetable vegetable section in my local Walmart?\u201d  My answer is YES #thc #cbd #cannabis #weedoil #mmj #wietolie #CB1 #CB2 #cancer #epileptic #opiatreplcement #AIDS https://t.co/CCdCwcbAvU", "first_save": 1635509975.555947, "hashtags": ["#THC", "#CBD", "#CANNABIS", "#WEEDOIL", "#MMJ", "#WIETOLIE", "#CB1", "#CB2", "#CANCER", "#EPILEPTIC", "#OPIATREPLCEMENT", "#AIDS"]}